nano_askllm/__init__.py
nano_askllm/askllm.py
nano_askllm-0.2.3.dist-info/LICENSE
nano_askllm-0.2.3.dist-info/METADATA
nano_askllm-0.2.3.dist-info/WHEEL
nano_askllm-0.2.3.dist-info/RECORD
