Metadata-Version: 2.1
Name: nano-askllm
Version: 0.2.3
Summary: Unofficial implementation of the Ask-LLM paper 'How to Train Data-Efficient LLMs', arXiv:2402.09668.
Home-page: https://github.com/susumuota/nano-askllm
Keywords: transformers,llm,large language model,pre-training,language model
Author: Susumu OTA
Author-email: 1632335+susumuota@users.noreply.github.com
Requires-Python: >=3.9,<4.0
Classifier: Programming Language :: Python :: 3
Classifier: Programming Language :: Python :: 3.9
Classifier: Programming Language :: Python :: 3.10
Classifier: Programming Language :: Python :: 3.11
Classifier: Topic :: Software Development :: Libraries :: Python Modules
Requires-Dist: torch (>=2.1.0,<3.0.0)
Requires-Dist: transformers (>=4.38.2,<5.0.0)
Project-URL: Documentation, https://github.com/susumuota/nano-askllm#readme
Project-URL: Repository, https://github.com/susumuota/nano-askllm
